Workbook
Name Slicer_MONTH: #N/A
Name Slicer_YEAR: #N/A

Sheet Financial Overview
AH2: =GETPIVOTDATA("[Measures].[Actual Revenue]",pivot_table!$J$15) -> 17958470
AH4: =GETPIVOTDATA("[Measures].[Actual Revenue]",pivot_table!$D$5,"[Date_table].[YEAR]","[Date_table].[YEAR].&[2024]") -> 0.42098539
AH6: =IFERROR(IF(AH4>=0," ▲ +"&TEXT(AH4,"0.0%"),"▼ "&TEXT(AH4,"0.0%")),"") -> ▲ +42.1%
AH7: =GETPIVOTDATA("[Measures].[Profit]",pivot_table!$K$20) -> -1448500
AH8: =GETPIVOTDATA("[Measures].[Profit]",pivot_table!$L$7,"[Date_table].[YEAR]","[Date_table].[YEAR].&[2024]") -> -1.2199971
AH9: =(IFERROR(IF(AH8>=0," ▲ +"&TEXT(AH8,"0.0%"),"▼ "&TEXT(AH8,"0.0%")),"")) -> ▼ -122.0%
AH12: =GETPIVOTDATA("[Measures].[Total Budget]",pivot_table!$B$13) -> 36923858
AH14: =GETPIVOTDATA("[Measures].[Budget Variance %]",pivot_table!$O$40) -> #REF!
AH16: =IF(AH14>=0," ▲ +"&TEXT(AH14,"0.0%"),"▼ "&TEXT(AH14,"0.0%")) -> #REF!
AI18: =pivot_table!D17 -> -0.011959273 | AJ18: =(IFERROR(IF(AI18>=0," ▼ +"&TEXT(AI18,"0.0%"),"▲"&TEXT(AI18,"0.0%")),"")) -> ▲-1.2%
AH19: =GETPIVOTDATA("[Measures].[Actual Expenses]",pivot_table!$M$15) -> 19406970
AH21: =GETPIVOTDATA("[Measures].[Budgeted Expenses]",pivot_table!$I$20) -> 19948888
AH23: =GETPIVOTDATA("[Measures].[Total Variance]",pivot_table!$G$18) -> -441582.5
AK24: =IF(AH4>=0," ▼ +"&TEXT(AH4,"0.0%")," ▲ "&TEXT(AH4,"0.0%")) -> ▼ +42.1%
AH25: =GETPIVOTDATA("[Measures].[Actual Expenses]",pivot_table!$I$6,"[Date_table].[YEAR]","[Date_table].[YEAR].&[2024]") -> 0.12145841
AH26: =IF(AH25>=0," ▲ +"&TEXT(AH25,"0.0%"),"▼ "&TEXT(AH25,"0.0%")) -> ▲ +12.1%
AH28: =GETPIVOTDATA("[Measures].[Expense Variance]",pivot_table!$A$7) -> 541917.5
AH29: =pivot_table!O21 -> 0.027165299
AH30: =IF(AH29>=0," ▼ +"&TEXT(AH29,"0.0%")," ▲ "&TEXT(AH29,"0.0%")) -> ▼ +2.7% | AI30: ▼ +2.7%

Sheet Expense Analysis

Sheet Insights

Sheet pivot_table
B3: Total Transactions
B4: 37365440
D5: Row Labels | E5: Actual Revenue
D6: 2022 | I6: Row Labels | J6: Actual Expenses
A7: Expense Variance | D7: 2023 | E7: 0.92116103 | I7: 2022 | L7: Row Labels | M7: Profit
A8: 541917.5 | D8: 2024 | E8: 0.42098539 | I8: 2023 | J8: 1.0960576 | L8: 2022
D9: Grand Total | I9: 2024 | J9: 0.12145841 | L9: 2023 | M9: 2.5389408
I10: Grand Total | L10: 2024 | M10: -1.2199971
L11: Grand Total
B13: Total Budget
B14: 36923858
J15: Actual Revenue | M15: Actual Expenses
D16: =B14 - B4 -> -441582.5 | J16: 17958470 | M16: 19406970
D17: =D16/B14 -> -0.011959273
G18: Total Variance
G19: -441582.5 | O19: =GETPIVOTDATA("[Measures].[Budgeted Expenses]",$I$20) - GETPIVOTDATA("[Measures].[Actual Expenses]",$M$15) -> 541917.5
I20: Budgeted Expenses | K20: Profit
B21: Budget Variance | I21: 19948888 | K21: -1448500 | O21: =O19/GETPIVOTDATA("[Measures].[Budgeted Expenses]",$I$20) -> 0.027165299
B22: =GETPIVOTDATA("[Measures].[Total Variance]",pivot_table!$G$18) -> -441582.5
R29: Actual Expenses
R30: 19406970
O40: Profit
O41: -1448500

Sheet TRANSACTION
A1: ID | B1: DATE | C1: COD_ACCOUNT | D1: ACCOUNT | E1: Short_CLASS | F1: CLASS | G1: TRANSACTION_TYPE | H1: NAME | I1: MEMO/DESCRIPTION | J1: REVENUE/EXPENSES | K1: AMOUNT | L1: REVENUE_SOURCE
A2: 1 | B2: 44562 | C2: 40100 | D2: 40100 SaaS Revenue | E2: G&A | F2: General & Administrative | G2: Invoice | H2: TechCorp Inc | I2: January SaaS Subscription | J2: REVENUE | K2: 45000 | L2: =RIGHT(D2,LEN(D2)-6) -> SaaS Revenue
A3: 2 | B3: 44562 | C3: 40100 | D3: 40100 SaaS Revenue | E3: G&A | F3: General & Administrative | G3: Invoice | H3: DataFlow Ltd | I3: January SaaS Subscription | J3: REVENUE | K3: 38000 | L3: =RIGHT(D3,LEN(D3)-6) -> SaaS Revenue
A4: 3 | B4: 44562 | C4: 40200 | D4: 40200 Product Revenue | E4: G&A | F4: General & Administrative | G4: Invoice | H4: GlobalTech | I4: Product License - Enterprise | J4: REVENUE | K4: 75000 | L4: =RIGHT(D4,LEN(D4)-6) -> Product Revenue
A5: 4 | B5: 44566 | C5: 50100 | D5: 50100 Web Domain & Hosting Fees | E5: G&A | F5: General & Administrative | G5: Bill | H5: AWS | I5: Cloud Hosting - January | J5: EXPENSES | K5: 2000 | L5: =RIGHT(D5,LEN(D5)-6) -> Web Domain & Hosting Fees
A6: 5 | B6: 44566 | C6: 50200 | D6: 50200 Merchant Account Fees | E6: G&A | F6: General & Administrative | G6: Bill | H6: Stripe | I6: Payment Processing Fees | J6: EXPENSES | K6: 1500 | L6: =RIGHT(D6,LEN(D6)-6) -> Merchant Account Fees
A7: 6 | B7: 44571 | C7: 60100 | D7: 60100 Advertising & Marketing | E7: S&M | F7: Sales & Marketing | G7: Bill | H7: Google Ads | I7: Monthly Ad Spend | J7: EXPENSES | K7: 5000 | L7: =RIGHT(D7,LEN(D7)-6) -> Advertising & Marketing
A8: 7 | B8: 44571 | C8: 60100 | D8: 60100 Advertising & Marketing | E8: S&M | F8: Sales & Marketing | G8: Bill | H8: LinkedIn Ads | I8: Premium Advertising | J8: EXPENSES | K8: 8500 | L8: =RIGHT(D8,LEN(D8)-6) -> Advertising & Marketing
A9: 8 | B9: 44576 | C9: 60800 | D9: 60800 Payroll Expenses | E9: S&M | F9: Sales & Marketing | G9: Bill | H9: ADP | I9: Payroll - Sales Team | J9: EXPENSES | K9: 6500 | L9: =RIGHT(D9,LEN(D9)-6) -> Payroll Expenses
A10: 9 | B10: 44576 | C10: 60800 | D10: 60800 Payroll Expenses | E10: G&A | F10: General & Administrative | G10: Bill | H10: ADP | I10: Payroll - G&A Team | J10: EXPENSES | K10: 4500 | L10: =RIGHT(D10,LEN(D10)-6) -> Payroll Expenses
A11: 10 | B11: 44581 | C11: 61000 | D11: 61000 Travel, Meals & Entertainment | E11: S&M | F11: Sales & Marketing | G11: Expense | H11: Marriott | I11: Client Meeting Hotel Stay | J11: EXPENSES | K11: 2500 | L11: =RIGHT(D11,LEN(D11)-6) -> Travel, Meals & Entertainment
A12: 11 | B12: 44586 | C12: 60700 | D12: 60700 Professional Services | E12: G&A | F12: General & Administrative | G12: Bill | H12: Deloitte | I12: Monthly Accounting Services | J12: EXPENSES | K12: 4500 | L12: =RIGHT(D12,LEN(D12)-6) -> Professional Services
A13: 12 | B13: 44592 | C13: 70100 | D13: 70100 Interest Income | E13: G&A | F13: General & Administrative | G13: Deposit | H13: Bank | I13: Interest Income | J13: REVENUE | K13: 500 | L13: =RIGHT(D13,LEN(D13)-6) -> Interest Income
... A1390: 1389 | B1390: 45657 | C1390: 80200 | D1390: 80200 Interest Expense | E1390: G&A | F1390: General & Administrative | G1390: Bill | H1390: Bank | I1390: Loan Interest | J1390: EXPENSES | K1390: 2800 | L1390: =RIGHT(D1390,LEN(D1390)-6) -> Interest Expense

Sheet BUDGET
A1: ID | B1: DATE | C1: COD_ACCOUNT | D1: ACCOUNT | E1: Short_CLASS | F1: CLASS | G1: REVENUE/EXPENSES | H1: BUDGET
A2: 1 | B2: 44592 | C2: 40200 | D2: 40200 Product Revenue | E2: G&A | F2: General & Administrative | G2: REVENUE | H2: 70000
A3: 2 | B3: 44592 | C3: 40100 | D3: 40100 SaaS Revenue | E3: G&A | F3: General & Administrative | G3: REVENUE | H3: 80000
A4: 3 | B4: 44592 | C4: 50100 | D4: 50100 Web Domain & Hosting Fees | E4: G&A | F4: General & Administrative | G4: EXPENSES | H4: 4000
A5: 4 | B5: 44592 | C5: 50210 | D5: 50210 Product Costs | E5: G&A | F5: General & Administrative | G5: EXPENSES | H5: 6000
A6: 5 | B6: 44592 | C6: 60100 | D6: 60100 Advertising & Marketing | E6: G&A | F6: General & Administrative | G6: EXPENSES | H6: 13500
A7: 6 | B7: 44592 | C7: 60810 | D7: 60810 Salary & Wages | E7: G&A | F7: General & Administrative | G7: EXPENSES | H7: 11000
A8: 7 | B8: 44592 | C8: 60820 | D8: 60820 Payroll Taxes | E8: G&A | F8: General & Administrative | G8: EXPENSES | H8: 880
A9: 8 | B9: 44592 | C9: 60830 | D9: 60830 Health Insurance | E9: G&A | F9: General & Administrative | G9: EXPENSES | H9: 1100
A10: 9 | B10: 44592 | C10: 60840 | D10: 60840 Payroll Processing Fees | E10: G&A | F10: General & Administrative | G10: EXPENSES | H10: 275
A11: 10 | B11: 44592 | C11: 60710 | D11: 60710 Accounting Fees | E11: G&A | F11: General & Administrative | G11: EXPENSES | H11: 4500
A12: 11 | B12: 44592 | C12: 60720 | D12: 60720 Consulting Fees | E12: G&A | F12: General & Administrative | G12: EXPENSES | H12: 8000
A13: 12 | B13: 44592 | C13: 60730 | D13: 60730 Legal Fees | E13: G&A | F13: General & Administrative | G13: EXPENSES | H13: 5200
... A1230: 1229 | B1230: 45657 | C1230: 61030 | D1230: 61030 Travel | E1230: S&M | F1230: Sales & Marketing | G1230: EXPENSES | H1230: 10000

Sheet ACCOUNTS
A1: ID | B1: COD_ACCOUNT | C1: ACCOUNT | D1: REVENUE/EXPENSES | E1: LEVEL_01 | F1: LEVEL_02
A2: 1 | B2: 40200 | C2: 40200 Product Revenue | D2: REVENUE | E2: Income | F2: Non Recurring Income
A3: 2 | B3: 40100 | C3: 40100 SaaS Revenue | D3: REVENUE | E3: Income | F3: Recurring Income
A4: 3 | B4: 50210 | C4: 50210 Product Costs | D4: EXPENSES | E4: Cost of Goods Sold | F4: Product COGS
A5: 4 | B5: 50100 | C5: 50100 Web Domain & Hosting Fees | D5: EXPENSES | E5: Cost of Goods Sold | F5: SaaS COGS
A6: 5 | B6: 50200 | C6: 50200 Merchant Account Fees | D6: EXPENSES | E6: Cost of Goods Sold | F6: SaaS COGS
A7: 6 | B7: 60100 | C7: 60100 Advertising & Marketing | D7: EXPENSES | E7: Operating Expenses | F7: Advertising & Marketing
A8: 7 | B8: 60300 | C8: 60300 Conferences & Events | D8: EXPENSES | E8: Operating Expenses | F8: Advertising & Marketing
A9: 8 | B9: 60200 | C9: 60200 Bank Charges & Fees | D9: EXPENSES | E9: Operating Expenses | F9: Other G&A
A10: 9 | B10: 60400 | C10: 60400 Dues & Subscriptions | D10: EXPENSES | E10: Operating Expenses | F10: Other G&A
A11: 10 | B11: 60450 | C11: 60450 Merchant Account Fees | D11: EXPENSES | E11: Operating Expenses | F11: Other G&A
A12: 11 | B12: 60500 | C12: 60500 Insurance | D12: EXPENSES | E12: Operating Expenses | F12: Other G&A
A13: 12 | B13: 60600 | C13: 60600 Office Expenses | D13: EXPENSES | E13: Operating Expenses | F13: Other G&A
... A36: 35 | B36: 80200 | C36: 80200 Interest Expense | D36: EXPENSES | E36: Other Expense | F36: Other Expense

Sheet dim-category
A1: CLASS
A2: General & Administrative
A3: Research & Development
A4: Sales & Marketing
A5: Customer Support

Sheet dim_RevenueSource
A1: ID | B1: ACCOUNT | C1: Account_name | D1: REVENUE/EXPENSES
A2: 1 | B2: 40200 Product Revenue | C2: =RIGHT(B2,LEN(B2)-6) -> Product Revenue | D2: REVENUE
A3: 2 | B3: 40100 SaaS Revenue | C3: =RIGHT(B3,LEN(B3)-6) -> SaaS Revenue | D3: REVENUE
A4: 15 | B4: 70100 Interest Income | C4: =RIGHT(B4,LEN(B4)-6) -> Interest Income | D4: REVENUE

Sheet date_table
A1: DATE | B1: Year | C1: MONTH_NUMBER | D1: MONTH
A2: =DATE(2022,1,1) -> 44562 | B2: =YEAR(A2) -> 2022 | C2: =MONTH(A2) -> 1 | D2: =TEXT(A2,"MMM") -> Jan
A3: =A2 + 1 -> 44563 | B3: =YEAR(A3) -> 2022 | C3: =MONTH(A3) -> 1 | D3: =TEXT(A3,"MMM") -> Jan
A4: =A3 + 1 -> 44564 | B4: =YEAR(A4) -> 2022 | C4: =MONTH(A4) -> 1 | D4: =TEXT(A4,"MMM") -> Jan
A5: =A4 + 1 -> 44565 | B5: =YEAR(A5) -> 2022 | C5: =MONTH(A5) -> 1 | D5: =TEXT(A5,"MMM") -> Jan
A6: =A5 + 1 -> 44566 | B6: =YEAR(A6) -> 2022 | C6: =MONTH(A6) -> 1 | D6: =TEXT(A6,"MMM") -> Jan
A7: =A6 + 1 -> 44567 | B7: =YEAR(A7) -> 2022 | C7: =MONTH(A7) -> 1 | D7: =TEXT(A7,"MMM") -> Jan
A8: =A7 + 1 -> 44568 | B8: =YEAR(A8) -> 2022 | C8: =MONTH(A8) -> 1 | D8: =TEXT(A8,"MMM") -> Jan
A9: =A8 + 1 -> 44569 | B9: =YEAR(A9) -> 2022 | C9: =MONTH(A9) -> 1 | D9: =TEXT(A9,"MMM") -> Jan
A10: =A9 + 1 -> 44570 | B10: =YEAR(A10) -> 2022 | C10: =MONTH(A10) -> 1 | D10: =TEXT(A10,"MMM") -> Jan
A11: =A10 + 1 -> 44571 | B11: =YEAR(A11) -> 2022 | C11: =MONTH(A11) -> 1 | D11: =TEXT(A11,"MMM") -> Jan
A12: =A11 + 1 -> 44572 | B12: =YEAR(A12) -> 2022 | C12: =MONTH(A12) -> 1 | D12: =TEXT(A12,"MMM") -> Jan
A13: =A12 + 1 -> 44573 | B13: =YEAR(A13) -> 2022 | C13: =MONTH(A13) -> 1 | D13: =TEXT(A13,"MMM") -> Jan
A14: =A13 + 1 -> 44574 | B14: =YEAR(A14) -> 2022 | C14: =MONTH(A14) -> 1 | D14: =TEXT(A14,"MMM") -> Jan
... A1097: =A1096 + 1 -> 45657 | B1097: =YEAR(A1097) -> 2024 | C1097: =MONTH(A1097) -> 12 | D1097: =TEXT(A1097,"MMM") -> Dec

Sheet DICTIONARY
A1: Sheet | B1: Column | C1: Description
A2: TRANSACTION | B2: Id | C2: Unique identifier for the transaction record
A3: TRANSACTION | B3: DATE | C3: Date of the transaction
A4: TRANSACTION | B4: COD_ACCOUNT | C4: Code representing the financial account
A5: TRANSACTION | B5: ACCOUNT | C5: Description of the financial account
A6: TRANSACTION | B6: Short_CLASS | C6: Short classification label (e.g., G&A)
A7: TRANSACTION | B7: CLASS | C7: Full classification category (e.g., General & Administrative)
A8: TRANSACTION | B8: TRANSACTION_TYPE | C8: Type of transaction (e.g., Invoice, Bill)
A9: TRANSACTION | B9: NAME | C9: Name of the client or vendor
A10: TRANSACTION | B10: MEMO/DESCRIPTION | C10: Description or memo for the transaction
A11: TRANSACTION | B11: REVENUE/EXPENSES | C11: Indicates if the transaction is revenue or expense
A12: TRANSACTION | B12: AMOUNT | C12: Monetary value of the transaction
... A20: BUDGET | B20: BUDGET | C20: Planned or estimated monetary amount for the account
